CHANGES.txt
MANIFEST.in
README.txt
setup.py
PCloudCV.egg-info/PKG-INFO
PCloudCV.egg-info/SOURCES.txt
PCloudCV.egg-info/dependency_links.txt
PCloudCV.egg-info/requires.txt
PCloudCV.egg-info/top_level.txt
pcloudcv/__init__.py
pcloudcv/config.json
pcloudcv/log.py
pcloudcv/parseArguments.py
pcloudcv/pcloudcv.py
pcloudcv/socketConnection.py
pcloudcv/uploadData.py