Metadata-Version: 1.0
Name: PCloudCV
Version: 0.0.1
Summary: CloudCV Python APIs
Home-page: http://github.com/batra-mlp-lab/pcloudcv
Author: Harsh Agrawal, Dr. Dhruv Batra
Author-email: h.agrawal092@gmail.com, dbatra@vt.edu
License: LICENSE.txt
Platform: UNKNOWN
